U_2ls/U_2ls.py
U_2ls/__init__.py
U_2ls/__main__.py
U_2ls/cli.py
U_2ls/utils.py
u_2ls-0.1.1.dist-info/licenses/LICENSE
u_2ls-0.1.1.dist-info/METADATA
u_2ls-0.1.1.dist-info/WHEEL
u_2ls-0.1.1.dist-info/entry_points.txt
u_2ls-0.1.1.dist-info/top_level.txt
u_2ls-0.1.1.dist-info/RECORD
