Metadata-Version: 2.4
Name: U_2ls
Version: 0.1.1
Summary: This project serves to provide basic tools to make manual selections on interactive UMAPs and draw gradients using plotly and ipywidgets
Author-email: Robin Van Everbroeck <robin_ve@hotmail.com>
Maintainer-email: Robin Van Everbroeck <robin_ve@hotmail.com>
License: MIT
Project-URL: bugs, https://github.com/rveverbr-private/U_2ls/issues
Project-URL: changelog, https://github.com/rveverbr-private/U_2ls/blob/master/changelog.md
Project-URL: homepage, https://github.com/rveverbr-private/U_2ls
Requires-Python: >=3.10
License-File: LICENSE
Requires-Dist: numpy
Requires-Dist: pandas
Requires-Dist: scipy
Requires-Dist: scikit-learn
Requires-Dist: seaborn
Requires-Dist: scanpy
Requires-Dist: shapely
Requires-Dist: alphashape
Requires-Dist: plotly
Requires-Dist: ipywidgets
Requires-Dist: ipython
Requires-Dist: anywidget
Requires-Dist: ipywidgets
Provides-Extra: test
Requires-Dist: coverage; extra == "test"
Requires-Dist: pytest; extra == "test"
Requires-Dist: ruff; extra == "test"
Requires-Dist: ty; extra == "test"
Requires-Dist: ipdb; extra == "test"
Dynamic: license-file
